{
  "slug": "99-nights-forest-movie-bunny-class-dads-corner",
  "date": "2026-04-16",
  "title_en": "Dad's Corner: They're Making a MOVIE of 99 Nights in the Forest!",
  "title_ua": "Татів Куточок: За мотивами 99 Nights in the Forest знімають ФІЛЬМ!",
  "tg_post_en": "🎬 <b>Hold onto your lanterns, kids — 99 Nights is going to HOLLYWOOD!</b>\n\n🧔 Dad here, and I nearly spilled my coffee on the keyboard! 20th Century Studios (yep, Disney!) just snagged the movie rights to my favorite spooky survival game. 🌲\n\nOh, and the Easter Part 2 update just dropped the brand-new <b>Bunny Class</b>! 🐰 Faion says I'm too hyped for a dad... she might be right.\n\n<i>Read the full Dad's Corner scoop 👇</i>\n\n#Roblox #DadsCorner",
  "tg_post_ua": "🎬 <b>Тримайтеся за ліхтарики, друзі — 99 Nights їде в ГОЛЛІВУД!</b>\n\n🧔 Татусь на зв'язку, і я мало не розлив каву на клавіатуру! 20th Century Studios (так-так, ті самі з Disney!) викупили права на екранізацію моєї улюбленої лісової виживалки. 🌲\n\nА ще в оновленні Easter Part 2 з'явився новенький <b>Bunny Class</b>! 🐰 Файон каже, що тато занадто гайпиться... мабуть, вона має рацію.\n\n<i>Уся сенсація — в повній статті 👇</i>\n\n#Роблокс #ТатовийКуточок",
  "character": "dad",
  "article_type": "news",
  "image": "/images/99-nights-forest-movie-bunny-class-dads-corner.png",
  "published_en": true,
  "published_ua": true,
  "msg_id_en": 55,
  "msg_id_ua": 55
}